salgsanalyse/Salg_og_Semester.py
salgsanalyse/__init__.py
salgsanalyse/__main__.py
salgsanalyse/file_handling.py
salgsanalyse/main.py
salgsanalyse/readme.md
salgsanalyse/vareetelling.py
HC_salgsanalyse-1.0.2.dist-info/METADATA
HC_salgsanalyse-1.0.2.dist-info/WHEEL
HC_salgsanalyse-1.0.2.dist-info/top_level.txt
HC_salgsanalyse-1.0.2.dist-info/RECORD
