Metadata-Version: 2.1
Name: HC-salgsanalyse
Version: 1.0.2
Summary: Salgsanalyse for iZettle-excel dokument
Home-page: https://github.com/vegardjervell/salgsanalyse
Author: Vegard Gjeldvik Jervell
Author-email: vegard.g.j@icloud.com
License: UNKNOWN
Platform: UNKNOWN
Requires-Dist: pandas (==1.3.2)
Requires-Dist: numpy (==1.21.2)
Requires-Dist: openpyxl (==3.0.7)
